ptuparser/__init__.py
ptuparser/ptuparser.py
ptuparser-0.0.8.dist-info/METADATA
ptuparser-0.0.8.dist-info/WHEEL
ptuparser-0.0.8.dist-info/licenses/LICENSE
ptuparser-0.0.8.dist-info/RECORD
