Metadata-Version: 2.1
Name: ptuparser
Version: 0.0.8
Summary: A fast library to read Pico Quant's *.ptu files.
Project-URL: Homepage, https://github.com/vganjali/ptu
Project-URL: Bug Tracker, https://github.com/vganjali/ptu/issues
Author-email: Vahid Ganjalizadeh <vganjali@ucsc.edu>
License: MIT License
License-File: LICENSE
Classifier: License :: OSI Approved :: MIT License
Classifier: Operating System :: OS Independent
Classifier: Programming Language :: Python :: 3
Requires-Python: >=3.7
